qualtop_llmapi/__init__.py
qualtop_llmapi/__main__.py
qualtop_llmapi/docs.py
qualtop_llmapi/main.py
qualtop_llmapi/api/__init__.py
qualtop_llmapi/api/router.py
qualtop_llmapi/api/routes/__init__.py
qualtop_llmapi/api/routes/chat.py
qualtop_llmapi/api/routes/embeddings.py
qualtop_llmapi/models/__init__.py
qualtop_llmapi/models/chatgpt_embeddings.py
qualtop_llmapi/models/loading.py
qualtop_llmapi/models/prompts.py
qualtop_llmapi/models/rag.py
qualtop_llmapi/models/rag_sql.py
qualtop_llmapi/models/single_prompt.py
qualtop_llmapi-0.47.dist-info/LICENSE
qualtop_llmapi-0.47.dist-info/METADATA
qualtop_llmapi-0.47.dist-info/WHEEL
qualtop_llmapi-0.47.dist-info/entry_points.txt
qualtop_llmapi-0.47.dist-info/top_level.txt
qualtop_llmapi-0.47.dist-info/RECORD
