Metadata-Version: 2.1
Name: qualtop-llmapi
Version: 0.47
Summary: Experimental libraries for communication with LLMs.
Home-page: https://github.com/elmugrearturo/
Author: Arturo Curiel
Author-email: me@arturocuriel.com
Classifier: Programming Language :: Python :: 3
Classifier: License :: OSI Approved :: MIT License
Classifier: Operating System :: OS Independent
License-File: LICENSE
Requires-Dist: wheel
Requires-Dist: chromadb
Requires-Dist: openai
Requires-Dist: numpy
Requires-Dist: matplotlib
Requires-Dist: seaborn
Requires-Dist: pandas
Requires-Dist: scikit-learn
Requires-Dist: scipy
Requires-Dist: tiktoken
Requires-Dist: ppscore
Requires-Dist: networkx
Requires-Dist: langchain
Requires-Dist: csv-schema-inference
Requires-Dist: fastapi
Requires-Dist: llama-cpp-python
Requires-Dist: Unidecode
